vcarhilclient/Enums.py
vcarhilclient/__init__.py
vcarhilclient/drt_structures.py
vcarhilclient/emr_mrt_client.py
vcarhilclient/kunyi_hil_test.py
vcarhilclient/kunyi_ma.py
vcarhilclient/kunyi_mrt.py
vcarhilclient/kunyi_project.py
vcarhilclient/kunyi_util.py
vcarhilclient/minio_handld.py
vcarhilclient/mrt.dll
vcarhilclient/mrt_client_Logger.py
vcarhilclient/mrt_strunctures.py
vcarhilclient/signal_daq.py
vcarhilclient-1.1.1130.dist-info/LICENSE
vcarhilclient-1.1.1130.dist-info/METADATA
vcarhilclient-1.1.1130.dist-info/WHEEL
vcarhilclient-1.1.1130.dist-info/top_level.txt
vcarhilclient-1.1.1130.dist-info/RECORD
