Metadata-Version: 2.1
Name: vcarhilclient
Version: 1.1.1130
Summary: vcarhilclient
Home-page: 
Author: vcarsystem
Author-email: service@vcarsystem.com
Classifier: Programming Language :: Python :: 3
Classifier: License :: Other/Proprietary License
Classifier: Operating System :: OS Independent
Requires-Python: >=3.6
License-File: LICENSE
Requires-Dist: bitstring
